package core;

public interface Const {

  // constant pool tag
  int CONSTANT_Class = 7;
  int CONSTANT_Fieldref = 9;
  int CONSTANT_Methodref = 10;
  int CONSTANT_InterfaceMethodref = 11;
  int CONSTANT_String = 8;
  int CONSTANT_Integer = 3;
  int CONSTANT_Float = 4;
  int CONSTANT_Long = 5;
  int CONSTANT_Double = 6;
  int CONSTANT_NameAndType = 12;
  int CONSTANT_Utf8 = 1;
  int CONSTANT_MethodHandle = 15;
  int CONSTANT_MethodType = 16;
  int CONSTANT_Dynamic = 17;
  int CONSTANT_InvokeDynamic = 18;
  int CONSTANT_Module = 19;
  int CONSTANT_Package = 20;

  // opcode
  int OPC_NOP = 0;
  int OPC_ACONST_NULL = 1;
  int OPC_ICONST_M1 = 2;
  int OPC_ICONST_0 = 3;
  int OPC_ICONST_1 = 4;
  int OPC_ICONST_2 = 5;
  int OPC_ICONST_3 = 6;
  int OPC_ICONST_4 = 7;
  int OPC_ICONST_5 = 8;
  int OPC_LCONST_0 = 9;
  int OPC_LCONST_1 = 10;
  int OPC_FCONST_0 = 11;
  int OPC_FCONST_1 = 12;
  int OPC_FCONST_2 = 13;
  int OPC_DCONST_0 = 14;
  int OPC_DCONST_1 = 15;
  int OPC_BIPUSH = 16;
  int OPC_SIPUSH = 17;
  int OPC_LDC = 18;
  int OPC_LDC_W = 19;
  int OPC_LDC2_W = 20;
  int OPC_ILOAD = 21;
  int OPC_LLOAD = 22;
  int OPC_FLOAD = 23;
  int OPC_DLOAD = 24;
  int OPC_ALOAD = 25;
  int OPC_ILOAD_0 = 26;
  int OPC_ILOAD_1 = 27;
  int OPC_ILOAD_2 = 28;
  int OPC_ILOAD_3 = 29;
  int OPC_LLOAD_0 = 30;
  int OPC_LLOAD_1 = 31;
  int OPC_LLOAD_2 = 32;
  int OPC_LLOAD_3 = 33;
  int OPC_FLOAD_0 = 34;
  int OPC_FLOAD_1 = 35;
  int OPC_FLOAD_2 = 36;
  int OPC_FLOAD_3 = 37;
  int OPC_DLOAD_0 = 38;
  int OPC_DLOAD_1 = 39;
  int OPC_DLOAD_2 = 40;
  int OPC_DLOAD_3 = 41;
  int OPC_ALOAD_0 = 42;
  int OPC_ALOAD_1 = 43;
  int OPC_ALOAD_2 = 44;
  int OPC_ALOAD_3 = 45;
  int OPC_IALOAD = 46;
  int OPC_LALOAD = 47;
  int OPC_FALOAD = 48;
  int OPC_DALOAD = 49;
  int OPC_AALOAD = 50;
  int OPC_BALOAD = 51;
  int OPC_CALOAD = 52;
  int OPC_SALOAD = 53;
  int OPC_ISTORE = 54;
  int OPC_LSTORE = 55;
  int OPC_FSTORE = 56;
  int OPC_DSTORE = 57;
  int OPC_ASTORE = 58;
  int OPC_ISTORE_0 = 59;
  int OPC_ISTORE_1 = 60;
  int OPC_ISTORE_2 = 61;
  int OPC_ISTORE_3 = 62;
  int OPC_LSTORE_0 = 63;
  int OPC_LSTORE_1 = 64;
  int OPC_LSTORE_2 = 65;
  int OPC_LSTORE_3 = 66;
  int OPC_FSTORE_0 = 67;
  int OPC_FSTORE_1 = 68;
  int OPC_FSTORE_2 = 69;
  int OPC_FSTORE_3 = 70;
  int OPC_DSTORE_0 = 71;
  int OPC_DSTORE_1 = 72;
  int OPC_DSTORE_2 = 73;
  int OPC_DSTORE_3 = 74;
  int OPC_ASTORE_0 = 75;
  int OPC_ASTORE_1 = 76;
  int OPC_ASTORE_2 = 77;
  int OPC_ASTORE_3 = 78;
  int OPC_IASTORE = 79;
  int OPC_LASTORE = 80;
  int OPC_FASTORE = 81;
  int OPC_DASTORE = 82;
  int OPC_AASTORE = 83;
  int OPC_BASTORE = 84;
  int OPC_CASTORE = 85;
  int OPC_SASTORE = 86;
  int OPC_POP = 87;
  int OPC_POP2 = 88;
  int OPC_DUP = 89;
  int OPC_DUP_X1 = 90;
  int OPC_DUP_X2 = 91;
  int OPC_DUP2 = 92;
  int OPC_DUP2_X1 = 93;
  int OPC_DUP2_X2 = 94;
  int OPC_SWAP = 95;
  int OPC_IADD = 96;
  int OPC_LADD = 97;
  int OPC_FADD = 98;
  int OPC_DADD = 99;
  int OPC_ISUB = 100;
  int OPC_LSUB = 101;
  int OPC_FSUB = 102;
  int OPC_DSUB = 103;
  int OPC_IMUL = 104;
  int OPC_LMUL = 105;
  int OPC_FMUL = 106;
  int OPC_DMUL = 107;
  int OPC_IDIV = 108;
  int OPC_LDIV = 109;
  int OPC_FDIV = 110;
  int OPC_DDIV = 111;
  int OPC_IREM = 112;
  int OPC_LREM = 113;
  int OPC_FREM = 114;
  int OPC_DREM = 115;
  int OPC_INEG = 116;
  int OPC_LNEG = 117;
  int OPC_FNEG = 118;
  int OPC_DNEG = 119;
  int OPC_ISHL = 120;
  int OPC_LSHL = 121;
  int OPC_ISHR = 122;
  int OPC_LSHR = 123;
  int OPC_IUSHR = 124;
  int OPC_LUSHR = 125;
  int OPC_IAND = 126;
  int OPC_LAND = 127;
  int OPC_IOR = 128;
  int OPC_LOR = 129;
  int OPC_IXOR = 130;
  int OPC_LXOR = 131;
  int OPC_IINC = 132;
  int OPC_I2L = 133;
  int OPC_I2F = 134;
  int OPC_I2D = 135;
  int OPC_L2I = 136;
  int OPC_L2F = 137;
  int OPC_L2D = 138;
  int OPC_F2I = 139;
  int OPC_F2L = 140;
  int OPC_F2D = 141;
  int OPC_D2I = 142;
  int OPC_D2L = 143;
  int OPC_D2F = 144;
  int OPC_I2B = 145;
  int OPC_I2C = 146;
  int OPC_I2S = 147;
  int OPC_LCMP = 148;
  int OPC_FCMPL = 149;
  int OPC_FCMPG = 150;
  int OPC_DCMPL = 151;
  int OPC_DCMPG = 152;
  int OPC_IFEQ = 153;
  int OPC_IFNE = 154;
  int OPC_IFLT = 155;
  int OPC_IFGE = 156;
  int OPC_IFGT = 157;
  int OPC_IFLE = 158;
  int OPC_IF_ICMPEQ = 159;
  int OPC_IF_ICMPNE = 160;
  int OPC_IF_ICMPLT = 161;
  int OPC_IF_ICMPGE = 162;
  int OPC_IF_ICMPGT = 163;
  int OPC_IF_ICMPLE = 164;
  int OPC_IF_ACMPEQ = 165;
  int OPC_IF_ACMPNE = 166;
  int OPC_GOTO = 167;
  int OPC_JSR = 168;
  int OPC_RET = 169;
  int OPC_TABLESWITCH = 170;
  int OPC_LOOKUPSWITCH = 171;
  int OPC_IRETURN = 172;
  int OPC_LRETURN = 173;
  int OPC_FRETURN = 174;
  int OPC_DRETURN = 175;
  int OPC_ARETURN = 176;
  int OPC_RETURN = 177;
  int OPC_GETSTATIC = 178;
  int OPC_PUTSTATIC = 179;
  int OPC_GETFIELD = 180;
  int OPC_PUTFIELD = 181;
  int OPC_INVOKEVIRTUAL = 182;
  int OPC_INVOKESPECIAL = 183;
  int OPC_INVOKESTATIC = 184;
  int OPC_INVOKEINTERFACE = 185;
  int OPC_INVOKEDYNAMIC = 186;
  int OPC_NEW = 187;
  int OPC_NEWARRAY = 188;
  int OPC_ANEWARRAY = 189;
  int OPC_ARRAYLENGTH = 190;
  int OPC_ATHROW = 191;
  int OPC_CHECKCAST = 192;
  int OPC_INSTANCEOF = 193;
  int OPC_MONITORENTER = 194;
  int OPC_MONITOREXIT = 195;
  int OPC_WIDE = 196;
  int OPC_MULTIANEWARRAY = 197;
  int OPC_IFNULL = 198;
  int OPC_IFNONNULL = 199;
  int OPC_GOTO_W = 200;
  int OPC_JSR_W = 201;
}
